Metadata-Version: 2.1
Name: obsaq
Version: 0.0.0
Summary: A Python package for accessing observational air quality data
Home-page: https://github.com/envdes/obsaq
Author: Haofan Wang
Author-email: cuitwhf@gmail.com
License: MIT
Platform: UNKNOWN
Classifier: Development Status :: 2 - Pre-Alpha
Classifier: Intended Audience :: Science/Research
Classifier: License :: OSI Approved :: MIT License
Classifier: Natural Language :: English
Classifier: Operating System :: OS Independent
Classifier: Programming Language :: Python :: 3
Classifier: Topic :: Scientific/Engineering :: Atmospheric Science
License-File: LICENSE
